<?xml version="1.0" encoding="UTF-8"?>
<saml2:Assertion ID="0987654321fedcbaabcdef123467890"
	IssueInstant="2021-08-02T12:00:00Z" Version="2.0"
	xmlns:ds="http://www.w3.org/2000/09/xmldsig#" xmlns:saml2="urn:oasis:names:tc:SAML:2.0:assertion"
	xmlns:eid="http://bsi.bund.de/eID/" xmlns:xenc="http://www.w3.org/2001/04/xmlenc#"
	xmlns:xsi="http://www.w3.org/2001/XMLSchema-instance" xmlns:xs="http://www.w3.org/2001/XMLSchema">
	<saml2:Issuer>https://www.eid-service.bund.de</saml2:Issuer>
	<saml2:Subject>
		<saml2:NameID Format="urn:oasis:names:tc:SAML:2.0:nameid-format:transient">
			_6b69710c2d804b48356209c9788a661f
		</saml2:NameID>
		<saml2:SubjectConfirmation Method="urn:oasis:names:tc:SAML:2.0:cm:bearer">
			<saml2:SubjectConfirmationData Address="127.0.0.1"
				InResponseTo="1234567890abcdef1234567890abcdef" NotOnOrAfter="2021-08-02T12:05:00Z"
				Recipient="https://www.eservice.bund.de/processResponse" />
		</saml2:SubjectConfirmation>
	</saml2:Subject>
	<saml2:Conditions>
		<saml2:AudienceRestriction>
			<saml2:Audience>
				https://www.eservice.bund.de
			</saml2:Audience>
		</saml2:AudienceRestriction>
		<saml2:OneTimeUse />
	</saml2:Conditions>
	<saml2:AuthnStatement AuthnInstant="2021-08-02T12:00:00Z">
		<saml2:AuthnContext>
			<saml2:AuthnContextDeclRef>
				urn:oasis:names:tc:SAML:2.0:ac:classes:SmartcardPKI
			</saml2:AuthnContextDeclRef>
		</saml2:AuthnContext>
	</saml2:AuthnStatement>
	<saml2:AttributeStatement>
		<saml2:Attribute Name="DocumentValidity">
			<saml2:AttributeValue xsi:type="eid:DocumentValidityResultType"
				Version="1">
				<eid:ReferenceDate>2021-08-02</eid:ReferenceDate>
				<eid:Status>VALID</eid:Status>
			</saml2:AttributeValue>
		</saml2:Attribute>
		<saml2:Attribute Name="DocumentType">
			<saml2:AttributeValue xsi:type="xs:string">
				ID
			</saml2:AttributeValue>
		</saml2:Attribute>
		<saml2:Attribute Name="IssuingState">
			<saml2:AttributeValue xsi:type="xs:string">
				D
			</saml2:AttributeValue>
		</saml2:Attribute>
		<saml2:Attribute Name="DateOfExpiry">
			<saml2:AttributeValue xsi:type="xs:date">
				2029-10-31
			</saml2:AttributeValue>
		</saml2:Attribute>
		<saml2:Attribute Name="GivenNames">
			<saml2:AttributeValue xsi:type="xs:string">
				ERIKA
			</saml2:AttributeValue>
		</saml2:Attribute>
		<saml2:Attribute Name="FamilyNames">
			<saml2:AttributeValue xsi:type="xs:string">
				MUSTERMANN
			</saml2:AttributeValue>
		</saml2:Attribute>
		<saml2:Attribute Name="AcademicTitle">
			<saml2:AttributeValue xsi:type="xs:string" />
		</saml2:Attribute>
		<saml2:Attribute Name="DateOfBirth">
			<saml2:AttributeValue xsi:type="eid:GeneralDateType">
				<eid:DateString>19640812</eid:DateString>
				<eid:DateValue>1964-08-12</eid:DateValue>
			</saml2:AttributeValue>
		</saml2:Attribute>
		<saml2:Attribute Name="PlaceOfBirth">
			<saml2:AttributeValue xsi:type="eid:GeneralPlaceType">
				<eid:FreetextPlace>
					BERLIN
				</eid:FreetextPlace>
			</saml2:AttributeValue>
		</saml2:Attribute>
		<saml2:Attribute Name="Nationality">
			<saml2:AttributeValue xsi:type="xs:string">
				D
			</saml2:AttributeValue>
		</saml2:Attribute>
		<saml2:Attribute Name="BirthName" AttributeNotOnChip="true">
			<saml2:AttributeValue xsi:type="xs:string" />
		</saml2:Attribute>
		<saml2:Attribute Name="PlaceOfResidence">
			<saml2:AttributeValue xsi:type="eid:GeneralPlaceType">
				<eid:StructuredPlace>
					<eid:Street>HEIDESTRASSE 17</eid:Street>
					<eid:City>KÖLN</eid:City>
					<eid:Country>D</eid:Country>
					<eid:ZipCode>51147</eid:ZipCode>
				</eid:StructuredPlace>
			</saml2:AttributeValue>
		</saml2:Attribute>
		<saml2:Attribute Name="RestrictedID">
			<saml2:AttributeValue xsi:type="eid:RestrictedIDType">
				<eid:ID>
					01A4FB509CEBC6595151A4FB5F9C75C6FE01A4FB59CB655A4FB5F9C75C6FEE
				</eid:ID>
				<eid:ID2>
					5C6FE01A4FB59CB655A4FB5F9C75C6FEE01A4FB509CEBC6595151A4FB5F9C7
				</eid:ID2>
			</saml2:AttributeValue>
		</saml2:Attribute>
		<saml2:Attribute Name="AgeVerification">
			<saml2:AttributeValue xsi:type="eid:AgeVerificationResultType">
				<eid:Request>
					<eid:Age>
						18
					</eid:Age>
				</eid:Request>
				<eid:Result>
					<eid:FulfilsRequest>
						true
					</eid:FulfilsRequest>
				</eid:Result>
			</saml2:AttributeValue>
		</saml2:Attribute>
		<saml2:Attribute Name="PlaceVerification">
			<saml2:AttributeValue xsi:type="eid:PlaceVerificationResultType">
				<eid:Request>
					<eid:CommunityID>
						027605
					</eid:CommunityID>
				</eid:Request>
				<eid:Result>
					<eid:FulfilsRequest>
						true
					</eid:FulfilsRequest>
				</eid:Result>
			</saml2:AttributeValue>
		</saml2:Attribute>
		<saml2:Attribute Name="TransactionAttestation">
			<saml2:AttributeValue
			xsi:type="eid:TransactionAttestationResponseType">
				<eid:TransactionAttestationFormat>
					http://bsi.bund.de/eID/ExampleAttestationFormat
				</eid:TransactionAttestationFormat>
				<eid:TransactionAttestationData>
V6INOOUsHouL9nYaRwR6RpX5WzccQXv51bIvvpY4Lsbp/VOPvG1ozxQCjo6JOi4xAv9/6b8G2PxaVv8bwdpFR/CN05xsnzxijzfemooKwve3Fl3005OX6dwkVyNQlZxXaWb3eUcYPA\MEwHSkhzP25ZM/J+CQHHaqLih6JW6wxSvUbuD307sjzkeaMkjJr9tXI9QcUmGmpHBWEWwon56HkWKGL1Dl0XH4\YuYhKMsTj2yjUJNlLH8OAm9cEX0ptQJlVTMRvNGRk53eUESnfhtQrVSm9bS63v+A9sGPrRlUIquCpcusX1nZe6\omAzs2tY0S04+s1fNvgHXKmQi24wIdhhbtFPbB2n2j9dAB8xjfGgEcsG3wPMliP6d
				</eid:TransactionAttestationData>
			</saml2:AttributeValue>
		</saml2:Attribute>
		<saml2:Attribute Name="LevelOfAssurance">
			<saml2:AttributeValue
			xsi:type="eid:LevelOfAssuranceType">
				http://bsi.bund.de/eID/LoA/hoch
			</saml2:AttributeValue>
		</saml2:Attribute>
		<saml2:Attribute Name="EIDType">
			<saml2:AttributeValue
			xsi:type="eid:EIDTypeResponseType">
				<eid:CardCertified>USED</eid:CardCertified>
			</saml2:AttributeValue>
		</saml2:Attribute>
	</saml2:AttributeStatement>
</saml2:Assertion>
